handytat.py
handytat-0.2.0.dist-info/METADATA
handytat-0.2.0.dist-info/WHEEL
handytat-0.2.0.dist-info/RECORD
